{
  "id": "098d78a3-f721-4c89-9a70-ab707e8fbc3e",
  "label": {
    "entry": [
      {
        "key": "en",
        "value": [
          "Search"
        ]
      },
      {
        "key": "de",
        "value": [
          "Suche"
        ]
      }
    ]
  },
  "alias": [
    "Scene-7",
    "Search"
  ],
  "unit_type": "SCENE",
  "placement_config": {
    "location_id": "ddc5097e-1018-443d-b288-e27e3a247e5d",
    "transformation_frame_id": "Scene-7",
    "pose": {},
    "shape": {}
  },
  "scope": {
    "component": [
      "location-18",
      "location-20",
      "location-7",
      "scene",
      "scene-7"
    ]
  },
  "description": {},
  "service_config": [
    {
      "binding_config": {},
      "unit_id": "098d78a3-f721-4c89-9a70-ab707e8fbc3e",
      "service_description": {
        "service_template_id": "f75053d2-7345-4928-ade6-eb3b4486ced9",
        "service_type": "ACTIVATION_STATE_SERVICE",
        "pattern": "OPERATION",
        "meta_config": {}
      }
    },
    {
      "binding_config": {},
      "unit_id": "098d78a3-f721-4c89-9a70-ab707e8fbc3e",
      "service_description": {
        "service_template_id": "f75053d2-7345-4928-ade6-eb3b4486ced9",
        "service_type": "ACTIVATION_STATE_SERVICE",
        "meta_config": {}
      }
    }
  ],
  "meta_config": {},
  "enabling_state": {
    "value": "ENABLED"
  },
  "scene_config": {}
}