{
  "id": "61f05c52-ac8c-4336-b2ae-39b435050d27",
  "unit_template_config_id": "Gira_429496730210000_BUTTON_1",
  "label": {
    "entry": [
      {
        "key": "en",
        "value": [
          "suspend"
        ]
      }
    ]
  },
  "alias": [
    "Button-43",
    "suspend"
  ],
  "unit_host_id": "933f4d62-769a-4975-ad8d-45d36912b68b",
  "unit_type": "BUTTON",
  "placement_config": {
    "location_id": "81b9efa4-2dc9-432e-b47c-1d73021ff0f3",
    "transformation_frame_id": "Button-43",
    "pose": {},
    "shape": {}
  },
  "scope": {
    "component": [
      "home",
      "csra",
      "home",
      "living",
      "button",
      "suspend"
    ]
  },
  "description": {},
  "bound_to_unit_host": false,
  "service_config": [
    {
      "binding_config": {
        "binding_id": "OPENHAB",
        "meta_config": {
          "entry": [
            {
              "key": "OPENHAB_BINDING_CONFIG",
              "value": "2/3/11"
            },
            {
              "key": "OPENHAB_BINDING_ITEM_ID",
              "value": "Gira_5133__citec_csra_home_living__Button__suspend__ButtonStateService"
            }
          ]
        }
      },
      "unit_id": "61f05c52-ac8c-4336-b2ae-39b435050d27",
      "service_description": {
        "service_template_id": "1d50901a-5cc1-4595-9180-334c3f3317dc",
        "service_type": "BUTTON_STATE_SERVICE",
        "pattern": "PROVIDER"
      },
      "meta_config": {}
    }
  ],
  "meta_config": {},
  "enabling_state": {
    "value": "ENABLED"
  },
  "permission_config": {
    "owner_id": "",
    "owner_permission": {},
    "other_permission": {}
  }
}