{
  "id": "a7061002-3945-47e1-a346-6cb45b5fd3be",
  "unit_template_config_id": "b129b706-5d0f-4909-a027-8338a4446f91_POWER_SWITCH_2",
  "label": {
    "entry": [
      {
        "key": "en",
        "value": [
          "Door"
        ]
      },
      {
        "key": "de",
        "value": [
          "Tür"
        ]
      },
      {
        "key": "technical",
        "value": [
          "S1 A3"
        ]
      }
    ]
  },
  "alias": [
    "PowerSwitch-32"
  ],
  "unit_host_id": "01bbbce7-fa7d-4215-9105-fc44f9d6ead1",
  "unit_type": "POWER_SWITCH",
  "placement_config": {
    "location_id": "cff20d86-c7e8-4d12-87e1-ebc67c7e0c93",
    "transformation_frame_id": "PowerSwitch-32",
    "pose": {
      "translation": {
        "x": 0.0,
        "y": 0.0,
        "z": 0.0,
        "frame_id": ""
      },
      "rotation": {}
    },
    "shape": {
      "bounding_box": {
        "left_front_bottom": {
          "x": 0.0,
          "y": 0.0,
          "z": 0.0,
          "frame_id": ""
        },
        "width": 0.0,
        "depth": 0.0,
        "height": 0.0
      }
    }
  },
  "scope": {
    "component": [
      "location-18",
      "location-20",
      "location-7",
      "location-13",
      "location-9",
      "powerswitch",
      "powerswitch-32"
    ]
  },
  "description": {},
  "bound_to_unit_host": false,
  "service_config": [
    {
      "binding_config": {
        "binding_id": "OPENHAB",
        "meta_config": {
          "entry": [
            {
              "key": "OPENHAB_BINDING_ITEM_ID",
              "value": "Gira_1046__citec_csra_control__PowerSwitch__S1_C3__PowerStateService"
            }
          ]
        }
      },
      "unit_id": "a7061002-3945-47e1-a346-6cb45b5fd3be",
      "service_description": {
        "service_template_id": "c3724ed5-4092-4142-8355-c1aea22d208f",
        "service_type": "POWER_STATE_SERVICE",
        "meta_config": {}
      },
      "meta_config": {}
    },
    {
      "binding_config": {
        "binding_id": "OPENHAB",
        "meta_config": {
          "entry": [
            {
              "key": "OPENHAB_BINDING_CONFIG",
              "value": "5/1/2+5/1/10"
            },
            {
              "key": "OPENHAB_BINDING_ITEM_ID",
              "value": "Gira_1046__citec_csra_control__PowerSwitch__S1_C3__PowerStateService"
            }
          ]
        }
      },
      "unit_id": "a7061002-3945-47e1-a346-6cb45b5fd3be",
      "service_description": {
        "service_template_id": "c3724ed5-4092-4142-8355-c1aea22d208f",
        "service_type": "POWER_STATE_SERVICE",
        "pattern": "OPERATION",
        "meta_config": {}
      },
      "meta_config": {}
    }
  ],
  "meta_config": {
    "entry": [
      {
        "key": "INFRASTRUCTURE",
        "value": "true"
      }
    ]
  },
  "enabling_state": {
    "value": "ENABLED"
  },
  "permission_config": {
    "owner_id": "",
    "owner_permission": {},
    "other_permission": {}
  }
}